asas/__init__.py
asas/usercustomize.py
asas-2.0.0.dist-info/METADATA
asas-2.0.0.dist-info/WHEEL
asas-2.0.0.dist-info/top_level.txt
asas-2.0.0.dist-info/RECORD
