Metadata-Version: 2.4
Name: asas
Version: 2.0.0
Summary: # The asas library in Python prints the text written inside it, like the print function.
Author: Programmer Seo Hook : @LAEGER_MO : @sis_c
Dynamic: author
Dynamic: summary
